lokky/__init__.py
lokky/barray.py
lokky/pionmath.py
lokky/scripts/__init__.py
lokky/scripts/lokky_analyze.py
lokky/scripts/lokky_analyze2d.py
lokky-0.0.10.dist-info/licenses/LICENSE
lokky-0.0.10.dist-info/METADATA
lokky-0.0.10.dist-info/WHEEL
lokky-0.0.10.dist-info/entry_points.txt
lokky-0.0.10.dist-info/top_level.txt
lokky-0.0.10.dist-info/RECORD
