Metadata-Version: 2.4
Name: lokky
Version: 0.0.10
Summary: This package contains swarm algorithms
Author-email: Michael <onisoris@yandex.ru>
Maintainer-email: Michael <onisoris@yandex.ru>
License-Expression: MIT
Project-URL: Homepage, https://github.com/OnisOris/lokky
Project-URL: Documentation, https://onisoris.github.io/lokky
Project-URL: Repository, https://github.com/OnisOris/lokky.git
Project-URL: Issues, https://github.com/OnisOris/lokky/issues
Classifier: Development Status :: 3 - Alpha
Classifier: Intended Audience :: Developers
Classifier: Topic :: Software Development :: Build Tools
Classifier: Programming Language :: Python :: 3.10
Classifier: Programming Language :: Python :: 3.11
Classifier: Programming Language :: Python :: 3.12
Classifier: Programming Language :: Python :: 3.13
Requires-Python: >=3.10
License-File: LICENSE
Requires-Dist: numpy>=1.22.0
Provides-Extra: plotting
Requires-Dist: matplotlib>=3.10.1; extra == "plotting"
Dynamic: license-file
